happyaccidentsapi/__init__.py
happyaccidentsapi/_happyaccidentsapi.py
happyaccidentsapi/_token.py
happyaccidentsapi/enums.py
happyaccidentsapi/errors.py
happyaccidentsapi/models.py
happyaccidentsapi-0.0.3.dist-info/LICENSE
happyaccidentsapi-0.0.3.dist-info/METADATA
happyaccidentsapi-0.0.3.dist-info/WHEEL
happyaccidentsapi-0.0.3.dist-info/RECORD
