Metadata-Version: 2.1
Name: happyaccidentsapi
Version: 0.0.3
Summary: API Wrapper for HappyAccidents
Home-page: https://github.com/hoopengo/happyaccidentsapi
License: Apache-2.0
Keywords: api,happyaccidents,ai
Author: hoopengo
Author-email: hoopengo@yandex.ru
Requires-Python: >=3.8,<4.0
Classifier: Development Status :: 2 - Pre-Alpha
Classifier: Intended Audience :: Developers
Classifier: License :: OSI Approved :: Apache Software License
Classifier: Programming Language :: Python :: 3
Classifier: Programming Language :: Python :: 3.8
Classifier: Programming Language :: Python :: 3.9
Classifier: Programming Language :: Python :: 3.10
Classifier: Programming Language :: Python :: 3.11
Classifier: Programming Language :: Python :: 3.12
Classifier: Topic :: Software Development :: Libraries
Classifier: Topic :: Software Development :: Libraries :: Python Modules
Classifier: Topic :: Utilities
Requires-Dist: aiofiles (>=23.1.0,<24.0.0)
Requires-Dist: aiohttp[speedups] (>=3.8.4,<4.0.0)
Requires-Dist: pydantic (>=2.0.0,<3.0.0)
Project-URL: Repository, https://github.com/hoopengo/happyaccidentsapi
